bacalhau_apiclient/__init__.py
bacalhau_apiclient/api_client.py
bacalhau_apiclient/configuration.py
bacalhau_apiclient/rest.py
bacalhau_apiclient/api/__init__.py
bacalhau_apiclient/api/compute_node_api.py
bacalhau_apiclient/api/misc_api.py
bacalhau_apiclient/api/ops_api.py
bacalhau_apiclient/api/orchestrator_api.py
bacalhau_apiclient/api/utils_api.py
bacalhau_apiclient/models/__init__.py
bacalhau_apiclient/models/all_of_execution_allocated_resources.py
bacalhau_apiclient/models/all_of_execution_compute_state.py
bacalhau_apiclient/models/all_of_execution_desired_state.py
bacalhau_apiclient/models/all_of_execution_job.py
bacalhau_apiclient/models/all_of_execution_published_result.py
bacalhau_apiclient/models/all_of_execution_run_output.py
bacalhau_apiclient/models/all_of_gpu_vendor.py
bacalhau_apiclient/models/all_of_input_source_source.py
bacalhau_apiclient/models/all_of_job_state.py
bacalhau_apiclient/models/all_of_label_selector_requirement_operator.py
bacalhau_apiclient/models/all_of_state_execution_desired_state_type_state_type.py
bacalhau_apiclient/models/all_of_state_execution_state_type_state_type.py
bacalhau_apiclient/models/all_of_state_job_state_type_state_type.py
bacalhau_apiclient/models/all_of_task_resources.py
bacalhau_apiclient/models/allocated_resources.py
bacalhau_apiclient/models/api_get_job_response.py
bacalhau_apiclient/models/api_get_node_response.py
bacalhau_apiclient/models/api_get_version_response.py
bacalhau_apiclient/models/api_http_credential.py
bacalhau_apiclient/models/api_list_job_executions_response.py
bacalhau_apiclient/models/api_list_job_history_response.py
bacalhau_apiclient/models/api_list_job_results_response.py
bacalhau_apiclient/models/api_list_jobs_response.py
bacalhau_apiclient/models/api_list_nodes_response.py
bacalhau_apiclient/models/api_put_job_request.py
bacalhau_apiclient/models/api_put_job_response.py
bacalhau_apiclient/models/api_put_node_request.py
bacalhau_apiclient/models/api_put_node_response.py
bacalhau_apiclient-1.4.1.dist-info/METADATA
bacalhau_apiclient-1.4.1.dist-info/WHEEL
bacalhau_apiclient-1.4.1.dist-info/RECORD
