Metadata-Version: 2.3
Name: bacalhau_apiclient
Version: 1.4.1
Summary: A Python client for the Bacalhau public API - https://github.com/bacalhau-project/bacalhau/tree/main/clients/python
Project-URL: Homepage, https://github.com/bacalhau-project/bacalhau/
Project-URL: Bug Tracker, https://github.com/bacalhau-project/bacalhau/issues
Author-email: Bacalhau Team <support@bacalhau.org>
Classifier: Operating System :: OS Independent
Classifier: Programming Language :: Python :: 3
Requires-Python: >=3.8
